{
    "name": "hetzner_virtualmachine",
    "description": "",
    "status": "implementation",
    "user_id": "$synchro_user$",
    "notify_contact_id": "$contact_to_notify$",
    "scope_class": "VirtualMachine",
    "database_table_name": "synchro_data_hetzner_virtualmachine",
    "scope_restriction": "",
    "full_load_periodicity": "0",
    "reconciliation_policy": "use_attributes",
    "action_on_zero": "create",
    "action_on_one": "update",
    "action_on_multiple": "error",
    "delete_policy": "ignore",
    "delete_policy_update": "",
    "delete_policy_retention": "0",
    "attribute_list": [
            {
                    "attcode": "applicationsolution_list",
                    "update": "0",
                    "reconcile": "0",
                    "update_policy": "master_unlocked",
                    "row_separator": "|",
                    "attribute_separator": ";",
                    "value_separator": ":",
                    "attribute_qualifier": "'",
                    "finalclass": "SynchroAttLinkSet",
                    "friendlyname": "applicationsolution_list"
            },
            {
                    "attcode": "business_criticity",
                    "update": "0",
                    "reconcile": "0",
                    "update_policy": "master_unlocked",
                    "finalclass": "SynchroAttribute",
                    "friendlyname": "business_criticity"
            },
            {
                    "attcode": "contacts_list",
                    "update": "0",
                    "reconcile": "0",
                    "update_policy": "master_unlocked",
                    "row_separator": "|",
                    "attribute_separator": ";",
                    "value_separator": ":",
                    "attribute_qualifier": "'",
                    "finalclass": "SynchroAttLinkSet",
                    "friendlyname": "contacts_list"
            },
            {
                    "attcode": "cpu",
                    "update": "0",
                    "reconcile": "0",
                    "update_policy": "master_unlocked",
                    "finalclass": "SynchroAttribute",
                    "friendlyname": "cpu"
            },
            {
                    "attcode": "description",
                    "update": "0",
                    "reconcile": "0",
                    "update_policy": "master_unlocked",
                    "finalclass": "SynchroAttribute",
                    "friendlyname": "description"
            },
            {
                    "attcode": "documents_list",
                    "update": "0",
                    "reconcile": "0",
                    "update_policy": "master_unlocked",
                    "row_separator": "|",
                    "attribute_separator": ";",
                    "value_separator": ":",
                    "attribute_qualifier": "'",
                    "finalclass": "SynchroAttLinkSet",
                    "friendlyname": "documents_list"
            },
            {
                    "attcode": "logicalvolumes_list",
                    "update": "0",
                    "reconcile": "0",
                    "update_policy": "master_unlocked",
                    "row_separator": "|",
                    "attribute_separator": ";",
                    "value_separator": ":",
                    "attribute_qualifier": "'",
                    "finalclass": "SynchroAttLinkSet",
                    "friendlyname": "logicalvolumes_list"
            },
            {
                    "attcode": "managementip",
                    "update": "1",
                    "reconcile": "0",
                    "update_policy": "master_locked",
                    "finalclass": "SynchroAttribute",
                    "friendlyname": "managementip"
            },
            {
                    "attcode": "move2production",
                    "update": "1",
                    "reconcile": "0",
                    "update_policy": "master_locked",
                    "finalclass": "SynchroAttribute",
                    "friendlyname": "move2production"
            },
            {
                    "attcode": "name",
                    "update": "1",
                    "reconcile": "1",
                    "update_policy": "master_locked",
                    "finalclass": "SynchroAttribute",
                    "friendlyname": "name"
            },
            {
                    "attcode": "org_id",
                    "update": "1",
                    "reconcile": "1",
                    "update_policy": "master_locked",
                    "reconciliation_attcode": "name",
                    "finalclass": "SynchroAttExtKey",
                    "friendlyname": "org_id"
            },
            {
                    "attcode": "osfamily_id",
                    "update": "1",
                    "reconcile": "0",
                    "update_policy": "master_locked",
                    "reconciliation_attcode": "name",
                    "finalclass": "SynchroAttExtKey",
                    "friendlyname": "osfamily_id"
            },
            {
                    "attcode": "oslicence_id",
                    "update": "0",
                    "reconcile": "0",
                    "update_policy": "master_unlocked",
                    "reconciliation_attcode": "",
                    "finalclass": "SynchroAttExtKey",
                    "friendlyname": "oslicence_id"
            },
            {
                    "attcode": "osversion_id",
                    "update": "1",
                    "reconcile": "0",
                    "update_policy": "master_locked",
                    "reconciliation_attcode": "name",
                    "finalclass": "SynchroAttExtKey",
                    "friendlyname": "osversion_id"
            },
            {
                    "attcode": "providercontracts_list",
                    "update": "0",
                    "reconcile": "0",
                    "update_policy": "master_unlocked",
                    "row_separator": "|",
                    "attribute_separator": ";",
                    "value_separator": ":",
                    "attribute_qualifier": "'",
                    "finalclass": "SynchroAttLinkSet",
                    "friendlyname": "providercontracts_list"
            },
            {
                    "attcode": "ram",
                    "update": "0",
                    "reconcile": "0",
                    "update_policy": "master_unlocked",
                    "finalclass": "SynchroAttribute",
                    "friendlyname": "ram"
            },
            {
                    "attcode": "services_list",
                    "update": "0",
                    "reconcile": "0",
                    "update_policy": "master_unlocked",
                    "row_separator": "|",
                    "attribute_separator": ";",
                    "value_separator": ":",
                    "attribute_qualifier": "'",
                    "finalclass": "SynchroAttLinkSet",
                    "friendlyname": "services_list"
            },
            {
                    "attcode": "status",
                    "update": "1",
                    "reconcile": "0",
                    "update_policy": "master_locked",
                    "finalclass": "SynchroAttribute",
                    "friendlyname": "status"
            },
            {
                    "attcode": "tickets_list",
                    "update": "0",
                    "reconcile": "0",
                    "update_policy": "master_unlocked",
                    "row_separator": "|",
                    "attribute_separator": ";",
                    "value_separator": ":",
                    "attribute_qualifier": "'",
                    "finalclass": "SynchroAttLinkSet",
                    "friendlyname": "tickets_list"
            },
            {
                    "attcode": "virtualhost_id",
                    "update": "1",
                    "reconcile": "1",
                    "update_policy": "master_locked",
                    "reconciliation_attcode": "name",
                    "finalclass": "SynchroAttExtKey",
                    "friendlyname": "virtualhost_id"
            }
    ],
    "user_delete_policy": "nobody",
    "url_icon": "",
    "url_application": ""
}